streamlit_aggrid_redux/__init__.py
streamlit_aggrid_redux/code.py
streamlit_aggrid_redux/errors.py
streamlit_aggrid_redux/grid_builder.py
streamlit_aggrid_redux/grid_options_builder.py
streamlit_aggrid_redux/grid_return.py
streamlit_aggrid_redux/types.py
streamlit_aggrid_redux/version.py
streamlit_aggrid_redux-2023.10.post1.dist-info/LICENSE
streamlit_aggrid_redux-2023.10.post1.dist-info/METADATA
streamlit_aggrid_redux-2023.10.post1.dist-info/WHEEL
streamlit_aggrid_redux-2023.10.post1.dist-info/top_level.txt
streamlit_aggrid_redux-2023.10.post1.dist-info/RECORD
